pytube/__init__.py
pytube/__main__.py
pytube/captions.py
pytube/cipher.py
pytube/cli.py
pytube/exceptions.py
pytube/extract.py
pytube/helpers.py
pytube/itags.py
pytube/monostate.py
pytube/query.py
pytube/request.py
pytube/streams.py
pytube/version.py
pytube/contrib/__init__.py
pytube/contrib/playlist.py
pytube4-0.1.1.dist-info/LICENSE
pytube4-0.1.1.dist-info/METADATA
pytube4-0.1.1.dist-info/WHEEL
pytube4-0.1.1.dist-info/entry_points.txt
pytube4-0.1.1.dist-info/top_level.txt
pytube4-0.1.1.dist-info/zip-safe
pytube4-0.1.1.dist-info/RECORD
