Metadata-Version: 2.1
Name: pytube4
Version: 0.1.1
Summary: Python 3 library for downloading YouTube Videos. Fork from pytube3, an unmaintained library.
Home-page: https://github.com/H4KKR/pytube4
Author: Max Booth, Nick Ficano, Harold Martin
Author-email: nficano@gmail.com, harold.martin@gmail.com
License: MIT
Project-URL: Bug Reports, https://github.com/hbmartin/pytube3/issues, https://github.com/H4KKR/pytube4/issues
Project-URL: Read the Docs, https://pytube3.readthedocs.io/en/latest/?badge=latest
Keywords: youtube,download,video,stream
Platform: UNKNOWN
Classifier: Development Status :: 5 - Production/Stable
Classifier: Environment :: Console
Classifier: Intended Audience :: Developers
Classifier: License :: OSI Approved :: MIT License
Classifier: Natural Language :: English
Classifier: Operating System :: MacOS
Classifier: Operating System :: Microsoft
Classifier: Operating System :: POSIX
Classifier: Operating System :: Unix
Classifier: Programming Language :: Python :: 3.6
Classifier: Programming Language :: Python :: 3.7
Classifier: Programming Language :: Python :: 3.8
Classifier: Programming Language :: Python
Classifier: Topic :: Internet
Classifier: Topic :: Multimedia :: Video
Classifier: Topic :: Software Development :: Libraries :: Python Modules
Classifier: Topic :: Terminals
Classifier: Topic :: Utilities
Requires-Python: >=3.6
